cnaas_yaml_cli/__init__.py
cnaas_yaml_cli/cli.py
cnaas_yaml_cli/cli_pre_model.py
cnaas_yaml_cli/reporef.rst
cnaas_yaml_cli/settingsrepo.py
cnaas_yaml_cli-0.0.6.dist-info/METADATA
cnaas_yaml_cli-0.0.6.dist-info/WHEEL
cnaas_yaml_cli-0.0.6.dist-info/licenses/LICENSE
cnaas_yaml_cli-0.0.6.dist-info/RECORD
